{
  "rootObjects": [
    {
      "id": "__00001__",
      "name": null
    }
  ],
  "objects": {
    "__00001__": {
      "_artists": "__00002__",
      "_idManager": "__00003__",
      "_playListGenerator": "__00004__",
      "_playLists": "__00005__",
      "_users": "__00006__"
    },
    "__00002__": {
      "0": "__00007__",
      "1": "__00008__",
      "2": "__00009__",
      "3": "__00010__",
      "4": "__00011__",
      "5": "__00012__",
      "6": "__00013__",
      "7": "__00014__"
    },
    "__00003__": {
      "_artistCounter": 8,
      "_trackCounter": 0,
      "_albumCounter": 22,
      "_playListCounter": 0,
      "_userCounter": 0
    },
    "__00004__": {},
    "__00005__": {},
    "__00006__": {},
    "__00007__": {
      "_id": 0,
      "_name": "gnr",
      "_country": "USA",
      "_albums": "__00015__"
    },
    "__00008__": {
      "_id": 1,
      "_name": "bon jovi",
      "_country": "USA",
      "_albums": "__00016__"
    },
    "__00009__": {
      "_id": 2,
      "_name": "tiago",
      "_country": "Argentina",
      "_albums": "__00017__"
    },
    "__00010__": {
      "_id": 3,
      "_name": "pearl jam",
      "_country": "USA",
      "_albums": "__00018__"
    },
    "__00011__": {
      "_id": 4,
      "_name": "gnr",
      "_country": "USA",
      "_albums": "__00019__"
    },
    "__00012__": {
      "_id": 5,
      "_name": "bon jovi",
      "_country": "USA",
      "_albums": "__00020__"
    },
    "__00013__": {
      "_id": 6,
      "_name": "tiago",
      "_country": "Argentina",
      "_albums": "__00021__"
    },
    "__00014__": {
      "_id": 7,
      "_name": "pearl jam",
      "_country": "USA",
      "_albums": "__00022__"
    },
    "__00015__": {},
    "__00016__": {},
    "__00017__": {},
    "__00018__": {},
    "__00019__": {},
    "__00020__": {},
    "__00021__": {},
    "__00022__": {}
  },
  "types": {
    "__00001__": "UNQfy",
    "__00002__": "Array",
    "__00003__": "IdManager",
    "__00004__": "PlayListGenerator",
    "__00005__": "Array",
    "__00006__": "Array",
    "__00007__": "Artist",
    "__00008__": "Artist",
    "__00009__": "Artist",
    "__00010__": "Artist",
    "__00011__": "Artist",
    "__00012__": "Artist",
    "__00013__": "Artist",
    "__00014__": "Artist",
    "__00015__": "Array",
    "__00016__": "Array",
    "__00017__": "Array",
    "__00018__": "Array",
    "__00019__": "Array",
    "__00020__": "Array",
    "__00021__": "Array",
    "__00022__": "Array"
  }
}